crisprzip/__init__.py
crisprzip/coarsegrain.py
crisprzip/kinetics.py
crisprzip/matrix_expon.py
crisprzip/nucleic_acid.py
crisprzip/plotting.py
crisprzip/landscape_params/average_params.json
crisprzip/landscape_params/average_params_legacy.json
crisprzip/landscape_params/sequence_params.json
crisprzip/nucleicacid_params/alkan2018.json
crisprzip/nucleicacid_params/banerjee2020.json
crisprzip/nucleicacid_params/santaluciahicks2004.json
crisprzip-1.2.2.dist-info/licenses/LICENSE
crisprzip-1.2.2.dist-info/METADATA
crisprzip-1.2.2.dist-info/WHEEL
crisprzip-1.2.2.dist-info/top_level.txt
crisprzip-1.2.2.dist-info/RECORD
