Metadata-Version: 2.4
Name: crisprzip
Version: 1.2.2
Summary: A kinetic model of CRISPR-Cas target recognition.
Author-email: HS Offerhaus <hsofferhaus@gmail.com>
Maintainer-email: HS Offerhaus <hsofferhaus@gmail.com>
License: MIT License
Project-URL: Homepage, https://github.com/hiddeoff/crisprzip
Project-URL: Documentation, https://hiddeoff.github.io/crisprzip/
Project-URL: Source, https://github.com/hiddeoff/crisprzip
Keywords: crispr-cas9,crispr,bioinformatics,genome editing,genetic engineering
Classifier: Development Status :: 5 - Production/Stable
Classifier: Intended Audience :: Developers
Classifier: Topic :: Scientific/Engineering
Classifier: License :: OSI Approved :: MIT License
Classifier: Programming Language :: Python :: 3
Classifier: Programming Language :: Python :: 3.10
Classifier: Programming Language :: Python :: 3.11
Classifier: Programming Language :: Python :: 3.12
Classifier: Programming Language :: Python :: 3 :: Only
Requires-Python: <3.13,>=3.10
License-File: LICENSE
Requires-Dist: numpy>=1.20
Requires-Dist: scipy>=1.7
Requires-Dist: matplotlib>=3.7
Requires-Dist: numba>=0.55
Provides-Extra: docs
Requires-Dist: sphinx>=1.3; extra == "docs"
Requires-Dist: myst-nb>=1.1; extra == "docs"
Requires-Dist: sphinx-rtd-theme>=3.0; extra == "docs"
Provides-Extra: jupyter
Requires-Dist: jupyter>=1.0; extra == "jupyter"
Provides-Extra: tests
Requires-Dist: pytest>=6.0; extra == "tests"
Requires-Dist: pandas>=2.0; extra == "tests"
Provides-Extra: distr
Requires-Dist: build; extra == "distr"
Requires-Dist: twine; extra == "distr"
Dynamic: license-file
